ovos_dinkum_listener/__init__.py
ovos_dinkum_listener/__main__.py
ovos_dinkum_listener/_util.py
ovos_dinkum_listener/plugins.py
ovos_dinkum_listener/service.py
ovos_dinkum_listener/transformers.py
ovos_dinkum_listener/version.py
ovos_dinkum_listener/res/snd/acknowledge.mp3
ovos_dinkum_listener/res/snd/error.mp3
ovos_dinkum_listener/res/snd/start_listening.wav
ovos_dinkum_listener/voice_loop/__init__.py
ovos_dinkum_listener/voice_loop/hotwords.py
ovos_dinkum_listener/voice_loop/voice_loop.py
ovos_dinkum_listener-0.5.0.dist-info/licenses/LICENSE
ovos_dinkum_listener-0.5.0.dist-info/METADATA
ovos_dinkum_listener-0.5.0.dist-info/WHEEL
ovos_dinkum_listener-0.5.0.dist-info/entry_points.txt
ovos_dinkum_listener-0.5.0.dist-info/top_level.txt
ovos_dinkum_listener-0.5.0.dist-info/RECORD
