Metadata-Version: 2.4
Name: ovos-dinkum-listener
Version: 0.5.0
Summary: ovos-core listener daemon client
Home-page: https://github.com/OpenVoiceOS/ovos-dinkum-listener
License: Apache-2.0
Classifier: Development Status :: 4 - Beta
Classifier: Programming Language :: Python :: 3
Classifier: License :: OSI Approved :: Apache Software License
License-File: LICENSE
Requires-Dist: ovos-plugin-manager<3.0.0,>=1.0.2
Requires-Dist: ovos-utils<1.0.0,>=0.8.1
Requires-Dist: ovos-config<3.0.0,>=1.2.2
Requires-Dist: ovos_bus_client<2.0.0,>=1.3.4
Requires-Dist: SpeechRecognition~=3.9
Provides-Extra: extras
Requires-Dist: ovos-stt-plugin-server<1.0.0,>=0.1.2; extra == "extras"
Requires-Dist: ovos-vad-plugin-silero<1.0.0,>=0.0.5; extra == "extras"
Requires-Dist: ovos-microphone-plugin-sounddevice<1.0.0,>=0.0.1; extra == "extras"
Requires-Dist: ovos-ww-plugin-vosk<1.0.0,>=0.1.7; extra == "extras"
Requires-Dist: ovos_ww_plugin_precise_onnx<1.0.0,>=0.0.1; extra == "extras"
Provides-Extra: linux
Requires-Dist: ovos-microphone-plugin-alsa<1.0.0,>=0.1.2; extra == "linux"
Provides-Extra: tests
Requires-Dist: pytest~=8.4; extra == "tests"
Requires-Dist: ovos-vad-plugin-webrtcvad; extra == "tests"
Requires-Dist: xdoctest~=1.1.5; extra == "tests"
Requires-Dist: pytest-cov>=3.0.0; extra == "tests"
Requires-Dist: coverage>=7.2.7; extra == "tests"
Dynamic: classifier
Dynamic: description
Dynamic: description-content-type
Dynamic: home-page
Dynamic: license
Dynamic: license-file
Dynamic: provides-extra
Dynamic: requires-dist
Dynamic: summary
